{
	"format_version": "1.8.0",
	"animations": {
		"idle": {
			"loop": true,
			"animation_length": 1.04,
			"bones": {
				"head": {
					"scale": {
						"0.0": {
							"vector": [1, 1, 1]
						},
						"0.52": {
							"vector": [0.96, 1, 1]
						},
						"1.04": {
							"vector": [1, 1, 1]
						}
					}
				},
				"Body": {
					"scale": {
						"0.0": {
							"vector": [1, 1, 1]
						},
						"0.52": {
							"vector": [1.05, 1, 1.02]
						},
						"1.04": {
							"vector": [1, 1, 1]
						}
					}
				},
				"RightArm": {
					"rotation": {
						"vector": [0, 0, 12.5]
					}
				},
				"LeftArm": {
					"rotation": {
						"vector": [0, 0, -12.5]
					}
				}
			}
		},
		"walk": {
			"loop": true,
			"animation_length": 0.47,
			"bones": {
				"head": {
					"position": {
						"0.0": {
							"vector": [0, 0, 0]
						},
						"0.12": {
							"vector": [0, 0, 0]
						},
						"0.16": {
							"vector": [0, -0.4, 0]
						},
						"0.2": {
							"vector": [0, 0, 0]
						},
						"0.36": {
							"vector": [0, 0, 0]
						},
						"0.4": {
							"vector": [0, -0.4, 0]
						},
						"0.44": {
							"vector": [0, 0, 0]
						}
					}
				},
				"Body": {
					"rotation": {
						"0.0": {
							"vector": [-4.99527, -0.21782, -2.4905]
						},
						"0.12": {
							"vector": [-5, 0, 0]
						},
						"0.24": {
							"vector": [-4.99527, 0.21782, 2.4905]
						},
						"0.36": {
							"vector": [-5, 0, 0]
						},
						"0.48": {
							"vector": [-4.99527, -0.21782, -2.4905]
						}
					},
					"position": {
						"0.0": {
							"vector": [0, 1, 0]
						},
						"0.12": {
							"vector": [0, -0.1, 0]
						},
						"0.24": {
							"vector": [0, 1, 0]
						},
						"0.36": {
							"vector": [0, -0.1, 0]
						},
						"0.48": {
							"vector": [0, 1, 0]
						}
					},
					"scale": {
						"0.0": {
							"vector": [1, 1.05, 1]
						},
						"0.12": {
							"vector": [1, 1, 1]
						},
						"0.24": {
							"vector": [1, 1.05, 1]
						},
						"0.36": {
							"vector": [1, 1, 1]
						},
						"0.48": {
							"vector": [1, 1.05, 1]
						}
					}
				},
				"RightArm": {
					"rotation": {
						"0.0": {
							"vector": [0, 0, 45]
						},
						"0.12": {
							"vector": [0, 0, 40]
						},
						"0.24": {
							"vector": [0, 0, 45]
						},
						"0.36": {
							"vector": [0, 0, 40]
						},
						"0.48": {
							"vector": [0, 0, 45]
						}
					}
				},
				"LeftArm": {
					"rotation": {
						"0.0": {
							"vector": [0, 0, -45]
						},
						"0.12": {
							"vector": [0, 0, -40]
						},
						"0.24": {
							"vector": [0, 0, -45]
						},
						"0.36": {
							"vector": [0, 0, -40]
						},
						"0.48": {
							"vector": [0, 0, -45]
						}
					}
				},
				"RightLeg": {
					"rotation": {
						"0.0": {
							"vector": [-35, 0, 0]
						},
						"0.12": {
							"vector": [0, 0, 0]
						},
						"0.24": {
							"vector": [35, 0, 0]
						},
						"0.36": {
							"vector": [0, 0, 0]
						},
						"0.48": {
							"vector": [-35, 0, 0]
						}
					}
				},
				"LeftLeg": {
					"rotation": {
						"0.0": {
							"vector": [35, 0, 0]
						},
						"0.12": {
							"vector": [0, 0, 0]
						},
						"0.24": {
							"vector": [-35, 0, 0]
						},
						"0.36": {
							"vector": [0, 0, 0]
						},
						"0.48": {
							"vector": [35, 0, 0]
						}
					}
				}
			}
		},
		"swim": {
			"loop": true,
			"animation_length": 0.48,
			"bones": {
				"head": {
					"position": {
						"0.0": {
							"vector": [0, 0, 0]
						},
						"0.12": {
							"vector": [0, 0, 0]
						},
						"0.16": {
							"vector": [0, -0.4, 0]
						},
						"0.2": {
							"vector": [0, 0, 0]
						},
						"0.36": {
							"vector": [0, 0, 0]
						},
						"0.4": {
							"vector": [0, -0.4, 0]
						},
						"0.44": {
							"vector": [0, 0, 0]
						}
					}
				},
				"Body": {
					"rotation": {
						"0.0": {
							"vector": [-4.99527, -0.21782, -2.4905]
						},
						"0.12": {
							"vector": [-5, 0, 0]
						},
						"0.24": {
							"vector": [-4.99527, 0.21782, 2.4905]
						},
						"0.36": {
							"vector": [-5, 0, 0]
						},
						"0.48": {
							"vector": [-4.99527, -0.21782, -2.4905]
						}
					},
					"position": {
						"0.0": {
							"vector": [0, 1, 0]
						},
						"0.12": {
							"vector": [0, -0.1, 0]
						},
						"0.24": {
							"vector": [0, 1, 0]
						},
						"0.36": {
							"vector": [0, -0.1, 0]
						},
						"0.48": {
							"vector": [0, 1, 0]
						}
					},
					"scale": {
						"0.0": {
							"vector": [1, 1.05, 1]
						},
						"0.12": {
							"vector": [1, 1, 1]
						},
						"0.24": {
							"vector": [1, 1.05, 1]
						},
						"0.36": {
							"vector": [1, 1, 1]
						},
						"0.48": {
							"vector": [1, 1.05, 1]
						}
					}
				},
				"RightArm": {
					"rotation": {
						"0.0": {
							"vector": [0, 0, 45]
						},
						"0.12": {
							"vector": [0, 0, 40]
						},
						"0.24": {
							"vector": [0, 0, 45]
						},
						"0.36": {
							"vector": [0, 0, 40]
						},
						"0.48": {
							"vector": [0, 0, 45]
						}
					}
				},
				"LeftArm": {
					"rotation": {
						"0.0": {
							"vector": [0, 0, -45]
						},
						"0.12": {
							"vector": [0, 0, -40]
						},
						"0.24": {
							"vector": [0, 0, -45]
						},
						"0.36": {
							"vector": [0, 0, -40]
						},
						"0.48": {
							"vector": [0, 0, -45]
						}
					}
				},
				"RightLeg": {
					"rotation": {
						"0.0": {
							"vector": [-35, 0, 0]
						},
						"0.12": {
							"vector": [0, 0, 0]
						},
						"0.24": {
							"vector": [35, 0, 0]
						},
						"0.36": {
							"vector": [0, 0, 0]
						},
						"0.48": {
							"vector": [-35, 0, 0]
						}
					}
				},
				"LeftLeg": {
					"rotation": {
						"0.0": {
							"vector": [35, 0, 0]
						},
						"0.12": {
							"vector": [0, 0, 0]
						},
						"0.24": {
							"vector": [-35, 0, 0]
						},
						"0.36": {
							"vector": [0, 0, 0]
						},
						"0.48": {
							"vector": [35, 0, 0]
						}
					}
				}
			}
		},
		"attack": {
			"animation_length": 0.24,
			"bones": {
				"Body": {
					"rotation": {
						"0.0": {
							"vector": [0, 0, 0]
						},
						"0.04": {
							"vector": [32.5, 0, 0]
						},
						"0.24": {
							"vector": [0, 0, 0]
						}
					}
				},
				"RightArm": {
					"rotation": {
						"0.0": {
							"vector": [0, 0, 12.5]
						},
						"0.04": {
							"vector": [-105, 0, 0]
						},
						"0.24": {
							"vector": [0, 0, 12.5]
						}
					}
				},
				"rightItem": {
					"rotation": {
						"0.0": {
							"vector": [0, 0, 0]
						},
						"0.04": {
							"vector": [52.5, 0, 0]
						},
						"0.24": {
							"vector": [0, 0, 0]
						}
					}
				},
				"LeftArm": {
					"rotation": {
						"vector": [0, 0, -12.5]
					}
				},
				"LeftLeg": {
					"rotation": {
						"0.0": {
							"vector": [0, 0, 0]
						},
						"0.04": {
							"vector": [-50, 0, 0]
						},
						"0.24": {
							"vector": [0, 0, 0]
						}
					}
				}
			}
		},
		"death": {
			"animation_length": 0.96,
			"bones": {
				"head": {
					"rotation": {
						"0.0": {
							"vector": [45, 0, 0]
						},
						"0.08": {
							"vector": [42.5, 0, 0]
						},
						"0.16": {
							"vector": [45, 0, 0]
						},
						"0.24": {
							"vector": [42.5, 0, 0]
						},
						"0.32": {
							"vector": [45, 0, 0]
						},
						"0.4": {
							"vector": [42.5, 0, 0]
						},
						"0.48": {
							"vector": [45, 0, 0]
						},
						"0.56": {
							"vector": [42.5, 0, 0]
						},
						"0.64": {
							"vector": [45, 0, 0]
						},
						"0.72": {
							"vector": [42.5, 0, 0]
						},
						"0.8": {
							"vector": [45, 0, 0]
						},
						"0.88": {
							"vector": [42.5, 0, 0]
						},
						"0.96": {
							"vector": [45, 0, 0]
						}
					}
				},
				"Body": {
					"rotation": {
						"0.0": {
							"vector": [-30, 0, 0]
						},
						"0.16": {
							"vector": [-30, 0, 0]
						},
						"0.32": {
							"vector": [-30, 0, 0]
						},
						"0.48": {
							"vector": [-30, 0, 0]
						},
						"0.64": {
							"vector": [-30, 0, 0]
						},
						"0.8": {
							"vector": [-30, 0, 0]
						},
						"0.96": {
							"vector": [-30, 0, 0]
						}
					},
					"position": {
						"0.0": {
							"vector": [0, 0, 0]
						},
						"0.16": {
							"vector": [0, -1, 0]
						},
						"0.32": {
							"vector": [0, -4, 0]
						},
						"0.48": {
							"vector": [0, -1, 0],
							"easing": "easeInOutSine"
						},
						"0.6": {
							"vector": [0, -4, 0],
							"easing": "easeInOutSine"
						}
					}
				},
				"RightArm": {
					"rotation": {
						"0.0": {
							"vector": [-39.75778, 4.81281, 5.7589]
						},
						"0.08": {
							"vector": [-39.32466, 7.9972, 9.63846]
						},
						"0.16": {
							"vector": [-39.75778, 4.81281, 5.7589]
						},
						"0.24": {
							"vector": [-39.32466, 7.9972, 9.63846]
						},
						"0.32": {
							"vector": [-39.75778, 4.81281, 5.7589]
						},
						"0.4": {
							"vector": [-39.32466, 7.9972, 9.63846]
						},
						"0.48": {
							"vector": [-39.75778, 4.81281, 5.7589]
						},
						"0.56": {
							"vector": [-39.32466, 7.9972, 9.63846]
						},
						"0.64": {
							"vector": [-39.75778, 4.81281, 5.7589]
						},
						"0.72": {
							"vector": [-39.32466, 7.9972, 9.63846]
						},
						"0.8": {
							"vector": [-39.75778, 4.81281, 5.7589]
						},
						"0.88": {
							"vector": [-39.32466, 7.9972, 9.63846]
						},
						"0.96": {
							"vector": [-39.75778, 4.81281, 5.7589]
						}
					}
				},
				"LeftArm": {
					"rotation": {
						"0.0": {
							"vector": [-55.86446, -16.76559, -11.06517]
						},
						"0.08": {
							"vector": [-56.59341, -12.60837, -8.19252]
						},
						"0.16": {
							"vector": [-55.86446, -16.76559, -11.06517]
						},
						"0.24": {
							"vector": [-56.59341, -12.60837, -8.19252]
						},
						"0.32": {
							"vector": [-55.86446, -16.76559, -11.06517]
						},
						"0.4": {
							"vector": [-56.59341, -12.60837, -8.19252]
						},
						"0.48": {
							"vector": [-55.86446, -16.76559, -11.06517]
						},
						"0.56": {
							"vector": [-56.59341, -12.60837, -8.19252]
						},
						"0.64": {
							"vector": [-55.86446, -16.76559, -11.06517]
						},
						"0.72": {
							"vector": [-56.59341, -12.60837, -8.19252]
						},
						"0.8": {
							"vector": [-55.86446, -16.76559, -11.06517]
						},
						"0.88": {
							"vector": [-56.59341, -12.60837, -8.19252]
						},
						"0.96": {
							"vector": [-55.86446, -16.76559, -11.06517]
						}
					}
				},
				"RightLeg": {
					"rotation": {
						"0.0": {
							"vector": [-65, 0, 0]
						},
						"0.08": {
							"vector": [-67.5, 0, 0]
						},
						"0.16": {
							"vector": [-65, 0, 0]
						},
						"0.24": {
							"vector": [-67.5, 0, 0]
						},
						"0.32": {
							"vector": [-65, 0, 0]
						},
						"0.4": {
							"vector": [-67.5, 0, 0]
						},
						"0.48": {
							"vector": [-65, 0, 0]
						},
						"0.56": {
							"vector": [-67.5, 0, 0]
						},
						"0.64": {
							"vector": [-65, 0, 0]
						},
						"0.72": {
							"vector": [-67.5, 0, 0]
						},
						"0.8": {
							"vector": [-65, 0, 0]
						},
						"0.88": {
							"vector": [-67.5, 0, 0]
						},
						"0.96": {
							"vector": [-65, 0, 0]
						}
					}
				},
				"LeftLeg": {
					"rotation": {
						"0.0": {
							"vector": [-47.5, 0, 0]
						},
						"0.08": {
							"vector": [-42.5, 0, 0]
						},
						"0.16": {
							"vector": [-47.5, 0, 0]
						},
						"0.24": {
							"vector": [-42.5, 0, 0]
						},
						"0.32": {
							"vector": [-47.5, 0, 0]
						},
						"0.4": {
							"vector": [-42.5, 0, 0]
						},
						"0.48": {
							"vector": [-47.5, 0, 0]
						},
						"0.56": {
							"vector": [-42.5, 0, 0]
						},
						"0.64": {
							"vector": [-47.5, 0, 0]
						},
						"0.72": {
							"vector": [-42.5, 0, 0]
						},
						"0.8": {
							"vector": [-47.5, 0, 0]
						},
						"0.88": {
							"vector": [-42.5, 0, 0]
						},
						"0.96": {
							"vector": [-47.5, 0, 0]
						}
					}
				}
			}
		}
	},
	"geckolib_format_version": 2
}